oslo_policy/__init__.py
oslo_policy/_cache_handler.py
oslo_policy/_checks.py
oslo_policy/_external.py
oslo_policy/_i18n.py
oslo_policy/_parser.py
oslo_policy/fixture.py
oslo_policy/generator.py
oslo_policy/opts.py
oslo_policy/policy.py
oslo_policy/shell.py
oslo_policy/sphinxext.py
oslo_policy/sphinxpolicygen.py
oslo_policy/version.py
oslo_policy/locale/en_GB/LC_MESSAGES/oslo_policy.po
oslo_policy/tests/__init__.py
oslo_policy/tests/base.py
oslo_policy/tests/test_cache_handler.py
oslo_policy/tests/test_checks.py
oslo_policy/tests/test_external.py
oslo_policy/tests/test_fixtures.py
oslo_policy/tests/test_generator.py
oslo_policy/tests/test_opts.py
oslo_policy/tests/test_parser.py
oslo_policy/tests/test_policy.py
oslo_policy/tests/test_shell.py
oslo_policy/tests/test_sphinxext.py
oslo_policy/tests/test_sphinxpolicygen.py
oslo_policy/tests/token_fixture.py
oslo_policy-4.8.0.dist-info/licenses/AUTHORS
oslo_policy-4.8.0.dist-info/licenses/LICENSE
oslo_policy-4.8.0.dist-info/METADATA
oslo_policy-4.8.0.dist-info/WHEEL
oslo_policy-4.8.0.dist-info/entry_points.txt
oslo_policy-4.8.0.dist-info/pbr.json
oslo_policy-4.8.0.dist-info/top_level.txt
oslo_policy-4.8.0.dist-info/RECORD
